qiskit_ignis_rb/__init__.py
qiskit_ignis_rb/circuits.py
qiskit_ignis_rb/data.py
qiskit_ignis_rb/fitters.py
qiskit_ignis_rb/rb_groups.py
qiskit_ignis_rb/rb_utils.py
qiskit_ignis_rb/utils.py
qiskit_ignis_rb-0.1.0.dist-info/LICENSE.txt
qiskit_ignis_rb-0.1.0.dist-info/METADATA
qiskit_ignis_rb-0.1.0.dist-info/WHEEL
qiskit_ignis_rb-0.1.0.dist-info/top_level.txt
qiskit_ignis_rb-0.1.0.dist-info/RECORD
