Metadata-Version: 2.1
Name: qiskit-ignis-rb
Version: 0.1.0
Summary: Fork of qiskit ignis with just RB
Home-page: https://github.com/qruise-ai/qiskit-ignis-rb
Author: Qiskit and Qruise team
Author-email: info@qruise.com
License: Apache-2.0
Project-URL: Documentation, https://pyscaffold.org/
Platform: any
Classifier: Development Status :: 4 - Beta
Classifier: Programming Language :: Python
License-File: LICENSE.txt
Requires-Dist: qiskit
Requires-Dist: importlib-metadata ; python_version < "3.8"
Provides-Extra: testing
Requires-Dist: setuptools ; extra == 'testing'
Requires-Dist: pytest ; extra == 'testing'
Requires-Dist: pytest-cov ; extra == 'testing'
